DSAinPython/README.md
DSAinPython/__init__.py
DSAinPython/tempCodeRunnerFile.py
DSAinPython/LinkedList/CircularLL.py
DSAinPython/LinkedList/DoublyLL.py
DSAinPython/LinkedList/SinglyLL.py
DSAinPython/Queue/ArrDEQueue.py
DSAinPython/Queue/ArrQueue.py
DSAinPython/Queue/LLDEQueue.py
DSAinPython/Queue/LLQueue.py
DSAinPython/Searching/BinarySearchIter.py
DSAinPython/Searching/BinarySearchRec.py
DSAinPython/Searching/LinearSearch.py
DSAinPython/Searching/__init__.py
DSAinPython/Sorting/BubbleSort.py
DSAinPython/Sorting/CountSort.py
DSAinPython/Sorting/InsertionSort.py
DSAinPython/Sorting/MergeSort.py
DSAinPython/Sorting/QuickSort.py
DSAinPython/Sorting/RadixSort.py
DSAinPython/Sorting/SelectionSort.py
DSAinPython/Sorting/ShellSort.py
DSAinPython/Stack/ArrStack.py
DSAinPython/Stack/LLStack.py
DSAinPython/Trees/BinaryTree.py
dimppy/README.md
dimppy/__init__.py
dimppy/tempCodeRunnerFile.py
dimppy/Algorithms/Greedy/FractionalKnapsack.py
dimppy/Algorithms/Greedy/IntervalSelection.py
dimppy/Graphs/AdjMatrix.py
dimppy/HashMap/Chaining.py
dimppy/HashMap/LinearProbing.py
dimppy/Heap/Heap.py
dimppy/Heap/tempCodeRunnerFile.py
dimppy/LinkedList/CircularLL.py
dimppy/LinkedList/DoublyLL.py
dimppy/LinkedList/SinglyLL.py
dimppy/Queue/ArrDEQueue.py
dimppy/Queue/ArrQueue.py
dimppy/Queue/LLDEQueue.py
dimppy/Queue/LLQueue.py
dimppy/Searching/BinarySearchIter.py
dimppy/Searching/BinarySearchRec.py
dimppy/Searching/LinearSearch.py
dimppy/Searching/__init__.py
dimppy/Sorting/BubbleSort.py
dimppy/Sorting/BucketSort.py
dimppy/Sorting/CountSort.py
dimppy/Sorting/HeapSort.py
dimppy/Sorting/InsertionSort.py
dimppy/Sorting/MergeSort.py
dimppy/Sorting/QuickSort.py
dimppy/Sorting/RadixSort.py
dimppy/Sorting/SelectionSort.py
dimppy/Sorting/ShellSort.py
dimppy/Stack/ArrStack.py
dimppy/Stack/LLStack.py
dimppy/Trees/BinarySearchTree.py
dimppy/Trees/BinaryTree.py
dimppy-1.0.0.0.dist-info/LICENSE.txt
dimppy-1.0.0.0.dist-info/METADATA
dimppy-1.0.0.0.dist-info/WHEEL
dimppy-1.0.0.0.dist-info/top_level.txt
dimppy-1.0.0.0.dist-info/RECORD
