Metadata-Version: 2.1
Name: dimppy
Version: 1.0.0.0
Summary: Data Structures implementation in Python
Home-page: https://github.com/Armaan-268/dimppy
Author: Armaan Chauhan
Author-email: armaanchauhan268@gmail.com
License: MIT
Keywords: datastructures,python
Platform: UNKNOWN
Classifier: Development Status :: 3 - Alpha
Classifier: Intended Audience :: Education
Classifier: Topic :: Software Development :: Libraries
Classifier: Operating System :: OS Independent
Classifier: License :: OSI Approved :: MIT License
Classifier: Programming Language :: Python :: 3
License-File: LICENSE.txt
Requires-Dist: numpy
